qurix/dataframe/__init__.py
qurix/dataframe/__version__.py
qurix/dataframe/anonymizer.py
tests/__init__.py
tests/test_anonymizer.py
qurix_dataframe_anonymizer-0.2.0.dist-info/METADATA
qurix_dataframe_anonymizer-0.2.0.dist-info/WHEEL
qurix_dataframe_anonymizer-0.2.0.dist-info/top_level.txt
qurix_dataframe_anonymizer-0.2.0.dist-info/RECORD
